ledger_fx_rates.py
ledger_fx_rates-1.0.0.dist-info/DESCRIPTION.rst
ledger_fx_rates-1.0.0.dist-info/METADATA
ledger_fx_rates-1.0.0.dist-info/RECORD
ledger_fx_rates-1.0.0.dist-info/WHEEL
ledger_fx_rates-1.0.0.dist-info/entry_points.txt
ledger_fx_rates-1.0.0.dist-info/metadata.json
ledger_fx_rates-1.0.0.dist-info/top_level.txt
