Metadata-Version: 2.0
Name: ledger-fx-rates
Version: 1.0.0
Summary: Render current foreign exchange rates from the European Central Bank as ledger market values.
Home-page: https://github.com/benwebber/ledger-fx-rates/
Author: Ben Webber
Author-email: benjamin.webber@gmail.com
License: UNKNOWN
Platform: UNKNOWN
Classifier: Development Status :: 5 - Production/Stable
Classifier: Programming Language :: Python :: 2
Classifier: Programming Language :: Python :: 2.7
Classifier: Programming Language :: Python :: 3
Classifier: Programming Language :: Python :: 3.4
Classifier: Programming Language :: Python :: 3.5
